cleanengine-0.1.2.dist-info/licenses/LICENSE
dataset_cleaner/__init__.py
dataset_cleaner/cli.py
dataset_cleaner/advanced/__init__.py
dataset_cleaner/advanced/advanced_analytics.py
dataset_cleaner/analysis/__init__.py
dataset_cleaner/analysis/analyzer.py
dataset_cleaner/analysis/statistical_tests.py
dataset_cleaner/analysis/time_series.py
dataset_cleaner/core/__init__.py
dataset_cleaner/core/cleaner.py
dataset_cleaner/interfaces/__init__.py
dataset_cleaner/interfaces/chatbot.py
dataset_cleaner/interfaces/folder_watcher.py
dataset_cleaner/interfaces/streamlit_app.py
dataset_cleaner/utils/__init__.py
dataset_cleaner/utils/config_manager.py
dataset_cleaner/utils/file_handler.py
dataset_cleaner/utils/logger_setup.py
dataset_cleaner/utils/rule_engine.py
scripts/__init__.py
scripts/create_sample_data.py
scripts/run_cleaner.py
scripts/run_tests.py
cleanengine-0.1.2.dist-info/METADATA
cleanengine-0.1.2.dist-info/WHEEL
cleanengine-0.1.2.dist-info/entry_points.txt
cleanengine-0.1.2.dist-info/top_level.txt
cleanengine-0.1.2.dist-info/RECORD
