Metadata-Version: 2.4
Name: cleanengine
Version: 0.1.2
Summary: The Ultimate Data Cleaning & Analysis Toolkit
Home-page: https://github.com/I-invincib1e/CleanEngine
Download-URL: https://github.com/I-invincib1e/CleanEngine/archive/v0.1.1.tar.gz
Author: CleanEngine Community
Author-email: CleanEngine Community <contact@cleanengine.com>
Maintainer-email: CleanEngine Community <contact@cleanengine.com>
License-Expression: MIT
Project-URL: Homepage, https://github.com/I-invincib1e/CleanEngine
Project-URL: Documentation, https://github.com/I-invincib1e/CleanEngine#readme
Project-URL: Repository, https://github.com/I-invincib1e/CleanEngine
Project-URL: Bug Tracker, https://github.com/I-invincib1e/CleanEngine/issues
Project-URL: Changelog, https://github.com/I-invincib1e/CleanEngine/blob/main/CHANGELOG.md
Keywords: data-cleaning,data-analysis,data-profiling,machine-learning,data-science,pandas,scikit-learn,data-validation,rule-engine,cli-tool,data-quality,outlier-detection,clustering,anomaly-detection,correlation-analysis,feature-importance,data-visualization,streamlit,yaml-config,automation
Platform: any
Classifier: Development Status :: 4 - Beta
Classifier: Intended Audience :: Developers
Classifier: Intended Audience :: Science/Research
Classifier: Operating System :: OS Independent
Classifier: Programming Language :: Python :: 3
Classifier: Programming Language :: Python :: 3.9
Classifier: Programming Language :: Python :: 3.10
Classifier: Programming Language :: Python :: 3.11
Classifier: Programming Language :: Python :: 3.12
Classifier: Topic :: Scientific/Engineering :: Information Analysis
Classifier: Topic :: Software Development :: Libraries :: Python Modules
Classifier: Topic :: Text Processing :: Filters
Classifier: Topic :: Database
Classifier: Topic :: Scientific/Engineering :: Artificial Intelligence
Classifier: Topic :: Scientific/Engineering :: Visualization
Requires-Python: >=3.9
License-File: LICENSE
Requires-Dist: pandas>=1.5.0
Requires-Dist: numpy>=1.21.0
Requires-Dist: scikit-learn>=1.1.0
Requires-Dist: scipy>=1.9.0
Requires-Dist: matplotlib>=3.5.0
Requires-Dist: seaborn>=0.11.0
Requires-Dist: plotly>=5.0.0
Requires-Dist: kaleido>=0.2.1
Requires-Dist: pyyaml>=6.0
Requires-Dist: pyarrow>=8.0.0
Requires-Dist: fastparquet>=0.8.0
Requires-Dist: openpyxl>=3.0.0
Requires-Dist: xlrd>=2.0.0
Requires-Dist: psutil>=5.8.0
Requires-Dist: rich>=12.0.0
Requires-Dist: typer[all]>=0.7.0
Requires-Dist: questionary>=1.10.0
Requires-Dist: watchdog>=2.1.0
Requires-Dist: streamlit>=1.20.0
Provides-Extra: dev
Requires-Dist: pytest>=7.0.0; extra == "dev"
Requires-Dist: pytest-cov>=4.0.0; extra == "dev"
Requires-Dist: pytest-mock>=3.10.0; extra == "dev"
Requires-Dist: black>=23.0.0; extra == "dev"
Requires-Dist: flake8>=6.0.0; extra == "dev"
Requires-Dist: mypy>=1.0.0; extra == "dev"
Requires-Dist: pre-commit>=3.0.0; extra == "dev"
Requires-Dist: tox>=4.0.0; extra == "dev"
Provides-Extra: docs
Requires-Dist: sphinx>=6.0.0; extra == "docs"
Requires-Dist: sphinx-rtd-theme>=1.2.0; extra == "docs"
Requires-Dist: myst-parser>=1.0.0; extra == "docs"
Requires-Dist: sphinx-autodoc-typehints>=1.23.0; extra == "docs"
Provides-Extra: full
Requires-Dist: jupyter>=1.0.0; extra == "full"
Requires-Dist: ipython>=8.0.0; extra == "full"
Requires-Dist: notebook>=6.5.0; extra == "full"
Dynamic: author
Dynamic: download-url
Dynamic: home-page
Dynamic: license-file
Dynamic: platform
Dynamic: requires-python
